Metadata-Version: 2.1
Name: igqloo
Version: 0.1
Summary: A simple command-line tool for writing GQL queries
Home-page: https://github.com/gerhalt/igqloo
Author: Josh Mottaz
Author-email: gerhalt@gmail.com
License: UNKNOWN
Keywords: graphql,gql,cli,queries,development
Platform: UNKNOWN
Classifier: Development Status :: 3 - Alpha
Classifier: Intended Audience :: Developers
Classifier: Programming Language :: Python :: 3
Classifier: Programming Language :: Python :: 3.8
Classifier: Programming Language :: Python :: 3.9
Classifier: Programming Language :: Python :: 3 :: Only
Requires-Python: >=3.8, <4
Provides-Extra: dev
Provides-Extra: test
